pyloggerx/__init__.py
pyloggerx/adapters.py
pyloggerx/config.py
pyloggerx/core.py
pyloggerx/exporters.py
pyloggerx/filters.py
pyloggerx/formatters.py
pyloggerx/handlers.py
pyloggerx/monitoring.py
pyloggerx/utils.py
pyloggerx-1.0.0.dist-info/licenses/LICENSE
pyloggerx-1.0.0.dist-info/METADATA
pyloggerx-1.0.0.dist-info/WHEEL
pyloggerx-1.0.0.dist-info/entry_points.txt
pyloggerx-1.0.0.dist-info/top_level.txt
pyloggerx-1.0.0.dist-info/RECORD
