Metadata-Version: 2.4
Name: pyloggerx
Version: 1.0.0
Summary: Modern, colorful and simple logging for Python
Home-page: https://github.com/Moesthetics-code/pyloggerx
Author: Mohamed NDIAYE
Author-email: Mohamed NDIAYE <mintok2000@gmail.com>
License: MIT
Project-URL: Homepage, https://github.com/Moesthetics-code/pyloggerx
Project-URL: Documentation, https://pyloggerx.readthedocs.io
Project-URL: Repository, https://github.com/Moesthetics-code/pyloggerx
Project-URL: Bug Reports, https://github.com/Moesthetics-code/pyloggerx/issues
Keywords: logging,colorful,json,rotation,modern
Classifier: Development Status :: 4 - Beta
Classifier: Intended Audience :: Developers
Classifier: License :: OSI Approved :: MIT License
Classifier: Operating System :: OS Independent
Classifier: Programming Language :: Python :: 3
Classifier: Programming Language :: Python :: 3.7
Classifier: Programming Language :: Python :: 3.8
Classifier: Programming Language :: Python :: 3.9
Classifier: Programming Language :: Python :: 3.10
Classifier: Programming Language :: Python :: 3.11
Classifier: Topic :: Software Development :: Libraries :: Python Modules
Classifier: Topic :: System :: Logging
Requires-Python: >=3.7
License-File: LICENSE
Provides-Extra: dev
Requires-Dist: pytest>=6.0; extra == "dev"
Requires-Dist: pytest-cov>=2.0; extra == "dev"
Requires-Dist: black>=21.0; extra == "dev"
Requires-Dist: flake8>=3.9; extra == "dev"
Requires-Dist: mypy>=0.900; extra == "dev"
Dynamic: author
Dynamic: home-page
Dynamic: license-file
Dynamic: requires-python
